{
  "id": "481bc5be2aca",
  "title": "静かなる問いから始まった、他者と向き合う旅路",
  "excerpt": "〜14週間の開発ジャーニーを追って〜...",
  "learnerId": "481bc5be2aca",
  "generatedAt": "2024-05-23 22:00:00",
  "storyType": "development_journey",
  "content": "# 【タイトル】: 静かなる問いから始まった、他者と向き合う旅路\n\n*〜14週間の開発ジャーニーを追って〜*\n\n## プロローグ: 問いの発見\n\n物語は、日常に潜む小さな「不便さ」への静かな眼差しから始まる。買い物中の合計金額、駐輪した場所、乾電池の残量。彼のバグリストには、誰もが一度は感じたことのある、ささやかな、しかし確かな生活の棘（とげ）が20個以上も並んでいた。\n\nその中に、ひときわ個人的で、切実な響きを持つ問いがあった。\n\n> 「手汗が多いので指紋認証がうまくいかない」\n> 「手汗でスマホがすぐベタベタになる」\n\n彼は、自分だけの「困りごと」だと思っていたのかもしれない。しかし、他者との対話が始まったとき、その認識は静かに、そして劇的に変化する。グループワークで、ある仲間が「家の鍵を閉めたか不安になる」と打ち明けた。その瞬間に、彼の心は強く揺さぶられた。\n\n> 「私も強迫性障害なので、家の鍵を閉めたかどうかはとても気になる。」\n\nそれは、初めて自らの特性を他者の困りごとと重ね合わせ、深く共感した瞬間だった。自分だけではなかった。この気づきは、小さな衝撃となって彼の心に波紋を広げた。「意外と自分だけだと思っていた困りごとを抱えている人は身近にいる」。この発見が、彼を内なる世界から、他者のいる世界へと誘う最初の扉となった。彼の開発の旅は、この「共感」という一点から、静かに幕を開けたのである。\n\n## 第一章: 価値を探して\n\n共感の発見は、彼を次なる問いへと導いた。「誰かのための価値とは何か？」。当初、彼は読書家としての自分自身の体験から、「読了済み本整理アプリ」というアイデアにたどり着く。読んだ本を間違えてまた借りてしまう、という小さな失敗を防ぐための、堅実で個人的な解決策だった。AIとの対話を通じて「手間と時間を省くことに価値があった」と気づき、一度はMVPとして形にする。\n\nしかし、彼の心は、もっと広く、もっと深い課題へと向かっていた。チームを組むにあたり、彼が提示したアイデアは、読書アプリではなく「毎日の食事健康管理アプリ」だった。\n\n> 「健康的でない食事により健康寿命を減らしてしまうことをなくしたい」\n\nそれは、個人的な「不便」の解消から、社会的な「不安」の解消へと、彼の視座が大きくシフトしたことを物語っていた。自分一人のためではなく、より多くの「誰か」のために。その「誰か」とは、健康に不安を抱えながらも、どうすればいいか分からない人々だ。彼は企画とアイデア出しにワクワクすると宣言し、「UIが作れるひと」という具体的な仲間を求めた。静かな共感から、能動的な価値創造へ。彼の旅は、仲間を得て、新たな大陸へと漕ぎ出した。\n\n## 第二章: 形にする挑戦\n\n仲間と共に「ヘルスラボ」と名付けられた船は、大きな海図を描き始めた。バリュープロポジションキャンバス（VPC）という航海図を前に、彼らは熱心に議論を交わす。「生活習慣病を改善したい」「献立を考えるのが面倒」。顧客の切実な声（Pains）に対し、「自動的に健康的な食事を提案する」「自炊を必要としない食事の提案」といった解決策（Pain Relievers）を書き込んでいく。\n\nそのプロセスで、彼は新たな発見をする。\n\n> 「一度、サービスを図に表してみることはとても良い考え方であると思った。」\n\n頭の中の漠然としたアイデアが、構造化され、チーム全員が共有できる「地図」へと変わっていく。その手応えを感じながらも、彼は満足していなかった。「プロダクトを良いものにする細かいサービスをまだまだ提案できる気がする」。そのためには何が必要か？彼は自問し、そして答えを見出す。「ユーザー目線に立ち、自分たちのサービスを使う想像をすることで足りない部分を見つける」。\n\nそれは、机上の空論で終わらせないという静かな決意表明だった。中間発表では、「ユーザーの栄養バランスを整えるツール」という目標を掲げ、プロジェクトの輪郭はより鮮明になっていった。しかし、この時点ではまだ、彼らの描く航路は、穏やかな海の上にあった。これから訪れる嵐を、彼らはまだ知らない。\n\n## 第三章: 現実との対話\n\n最初の嵐は、ユーザーインタビューという形で訪れた。彼らが信じていた「AIから健康的な献立を提案されると自炊する気になる」という価値仮説は、現実の前にあっけなく崩れ去る。\n\n> 「普段から自炊する習慣がない人は献立を提案されたくらいでは自炊しない。」\n\nインタビューから得られたフィードバックは、痛烈だった。「レシピの食材を毎日調達するのが難しい」「そもそも手間をかけたくない」。彼らの善意の提案は、ターゲットとする人々の生活実感とは乖離していたのだ。この厳しい現実は、チームに大きな方向転換を迫った。VPCには「🌟自炊を必要としない食事の提案」という、新たな星印が書き加えられた。\n\nさらに彼は、SNSでの仮ローンチや、肥満体型の社会人への直接の提案（アタック）に挑む。しかし、現実は甘くなかった。SNSでの反応は少なく、対面で提案した相手からは「無料なら考える」という厳しい答えが返ってきた。\n\n> 「反応が少なかったため、もう少しニーズに合った機能を考えたい。」\n> 「食事に手間をかけたくない」\n\n彼の言葉は、冷静に現実を受け止めている。しかしその裏には、自分たちの信じる価値が、なぜ届かないのかという焦りや葛藤があったはずだ。理想と現実の間に生まれた深い溝。それは、この旅における最大の試練であり、最も重要な学びの始まりでもあった。\n\n## 第四章: 本質への問い直し\n\n「お金を払ってでも使いたい」と言ってくれる顧客は見つからないまま、旅は終盤に差し掛かった。彼はその理由を「周りに食生活を気にしている人があまりいない」からだと分析する。しかし、それは表面的な理由に過ぎないことを、彼自身が一番よく分かっていたはずだ。彼は、さらに深く、本質的な問いへと沈んでいく。\n\n> 「自分たちのサービスの適切な顧客が使っているsnsを見極めて宣伝する必要がある。」\n\nこの気づきは、単なるマーケティング手法の反省ではない。「誰に、どう届けるか」という、この旅の出発点となった問いへの回帰だ。自分たちが届けたい価値は、本当に「その人」が必要としているものなのか？自分たちの声は、「その人」がいる場所に届いているのか？\n\nポスター発表では、「食事の偏り気になりませんか？」という大きな問いを掲げ、「食事記録、献立の提案、手軽な栄養管理」という本質的な価値だけをシンプルに提示した。多くの言葉を削ぎ落とし、本当に伝えたいことだけを残す。それは、厳しい現実との対話を経て、彼らがたどり着いた一つの答えだった。理想を語るだけでなく、相手の世界に寄り添い、相手の言葉で語りかけることの重要性。彼はこのプロセスを通じて、プロダクト開発とは、絶え間ない「他者理解」の旅なのだということを、身体で学んでいった。\n\n## エピローグ: 振り返りと学び\n\n14週間の旅路の終わり。彼は最終振り返りジャーナルに、チームの軌跡を淡々と、しかし誠実に記録した。\n\n> 仮説からの改善やピボット:\n> 「AI献立提案＝自炊の動機になる」は未達。→ 「非調理・即食系メニュー提案」へと視点を転換。\n\nこの一文に、彼の学びのすべてが凝縮されている。自分たちの思い込み（仮説）で突っ走るのではなく、他者の声に耳を傾け、しなやかに方向転換（ピボット）する勇気。うまくいかなかったことを「未達」と認め、次の一手へと繋げるしなやかさ。\n\n当初、彼は自分自身の「不便」や「特性」という内なる世界からスタートした。しかし、チームを組み、ユーザーと対話し、厳しい現実に直面する中で、彼の視線は着実に「他者」へと向けられていった。\n\nお金を払ってくれる顧客は見つからなかったかもしれない。プロダクトが商業的に成功したわけでもない。しかし、彼はこの旅を通じて、もっと大切なものを手に入れた。それは、他者の痛みに共感し、その人の世界を想像し、現実と向き合いながら価値を問い続けるという、開発者としての、そして一人の人間としての、誠実な姿勢そのものだ。\n\n静かな共感から始まった彼の物語は、これからも続くだろう。次に彼がどんな「問い」を見つけ、どんな「他者」と出会うのか。この旅で得たコンパスを手に、彼はまた新たな航海へと漕ぎ出していくに違いない。\n\n---\n\n### 付録: 開発ジャーニー概要\n\n- **期間**: 14週間\n- **提出課題数**: 16課題\n- **主要なピボット**:\n    1.  個人の課題（読書管理）からチームの課題（健康管理）へのシフト。\n    2.  「自炊を促す献立提案」から「自炊を必要としない手軽な食事提案」への価値転換。\n- **最終プロダクト**: **ヘルスラボ** - 記録・分析・献立提案を一体化し、手軽な栄養管理を支援する食事提案アプリ。\n- **核心的な学び**: 自身の仮説や理想が、必ずしもユーザーの現実とは一致しないこと。他者の声に真摯に耳を傾け、方向転換を恐れないことの重要性。\n\n---\n\n*この物語は、提供されたJSONデータをもとに、構成作家エージェントが執筆しました。（生成日時: 2024-05-23 22:00:00）*"
}