{
  "id": "b3e7070a5d57",
  "title": "「どこだっけ？」から始まった、誠実な問い直しの物語",
  "excerpt": "〜一人の学生が辿った、14週間の開発ジャーニーを追って〜...",
  "learnerId": "b3e7070a5d57",
  "generatedAt": "2024-05-23 15:00:00",
  "storyType": "development_journey",
  "content": "# 【タイトル】: 「どこだっけ？」から始まった、誠実な問い直しの物語\n\n*〜一人の学生が辿った、14週間の開発ジャーニーを追って〜*\n\n## プロローグ: 問いの発見\n\n物語は、日常に潜む小さな「不便さ」への気づきから始まった。この学生の目に映る世界は、無数の「バグ」で溢れていた。\n\n> 「連絡手段が多すぎて、どこからきた連絡だったか探してしまう」\n> 「冷蔵庫の中身を把握しきれず、同じものを買ってしまう」\n> 「スーパーで売り場がわからない」\n\n彼のバグリストには、誰もが一度は感じたことのある、けれど見過ごしてしまいがちな21個もの「あるある」が並ぶ。その視線は、テクノロジーがもたらす新たな煩わしさにも向けられていた。パスワード認証の面倒さ、偏りすぎるYouTubeのおすすめ、お節介なGoogle Mapの通知。\n\n彼の思考は、単なる不満の表明で終わらない。それぞれの「バグ」の隣には、解決策としての「イノベーション」の芽が記されていた。その中で、ひときわ彼の心を捉えたのは、情報の散逸という問題だった。\n\n> **「あの情報、どこだっけ？」**\n\nSlack、メール、SNS、Discord…。便利になるはずのツールが、逆に情報を分断し、私たちを迷子にさせている。この根源的な問いが、彼の14週間にわたる探求の出発点となった。それは、単なるアプリ開発の始まりではなく、「情報との付き合い方」そのものを問い直す、静かで誠実な旅の始まりでもあった。\n\n## 第一章: 価値を探して\n\n最初の問いは、まだ漠然としていた。しかし、他者との対話を通じて、その輪郭は少しずつ鮮明になっていく。\n\n第二回のブレイクアウトセッションで、彼は自分とは全く異なる他者の「困りごと」に耳を傾ける。「休日の過ごし方を決めるのが面倒」。計画を立てるのが好きな彼にとって、それは新鮮な驚きだった。なぜ、そんな悩みを持つのか。彼はその内面を想像する。「選択肢が多すぎる、損したくない、との意識が強すぎて迷って疲れてしまうのではないか？」。この共感のプロセスは、彼に「情報の海に溺れている人」という具体的なユーザー像を意識させた。\n\nそして、彼は自身の問いに立ち返る。散逸した情報をどうにかしたい。GPTとの壁打ちを通じて、彼はその価値を言語化していく。ターゲットは誰か？スタートアップのPM、コミュニティ運営者、研究者、リモートワーカー…。複数のプラットフォームを使いこなし、情報の分断に日々苦しんでいる人々の顔が浮かび上がった。\n\n届けたい価値は明確だった。「プラットフォームに依存しない『一括検索』の便利さ」。そして彼は、その価値を届けるための最初の“一皿”を考案する。\n\n> 「スクショをとって投げると、AIがプラットフォームと文字を読み取ってリスト化するアプリ」\n\nAPI連携のような高度な技術ではなく、あえて手軽なスクリーンショットという手段を選ぶ。それは「技術的難易度が低く、最速で仮説を確かめられる」から。彼の思考は、地に足がついていた。理想を追い求める前に、まず価値の本質を問いたい。その現実的な姿勢が、このアイデアには込められていた。\n\n## 第二章: 形にする挑戦\n\nアイデアは、仲間との出会いによってプロジェクトへと昇華する。「チーム さけび」の誕生だ。彼らは、多くの人が心の内で叫んでいるであろう「あれって、どこに書いてあったっけ？」という声に応えることを誓った。\n\nチーム憲章には、彼らの冷静な分析と野心的な目標が記されている。Raycast、Mem.aiといった競合サービスの存在を認めつつ、彼らは「圧倒的な横断性」という差別化ポイントを見出す。APIが提供されないツールや、リアルな場の情報すらも対象にするために、「スクショをAIで分析する」という独自のアプローチを武器に据えた。\n\n> 「他のサービスにない圧倒的な横断性を実現する。…これにより、APIがないプラットフォームや、単なるWEB上の情報、メールの文章などの旧来からあるプラットフォームの情報も対象になる。」\n\n目標は明確だ。「WEBアプリとして製作」し、仮説を検証する。しかし、彼の心には早くも小さな疑念の影が差し始めていた。VPC（価値提案キャンバス）の作成を振り返り、彼は率直に書き記す。\n\n> **「ペインは実在するが、解決策はこれでよいのか？と感じる。」**\n\nこの内省的な問いかけは、この後の旅路を決定づける重要な転換点となる。彼は焦っていたのかもしれない。「MVPを早く作って試してもらいたい」。頭で考えるのではなく、現実の世界に投じて、その反応を確かめたい。その一心で、彼は開発ツールとしてReplitを希望し、具体的な形にする挑戦へと突き進んでいった。\n\n## 第三章: 現実との対話\n\nプロジェクトは中間地点を迎える。ユーザーインタビュー、そして仮ローンチ。アイデアが初めて、現実の世界と対話する時が来た。\n\n最初のインタビューで得られた反応は、期待と懸念が入り混じったものだった。プラットフォームを横断してインデックスするというアイデアは「面白い」と評価された。しかし、同時に「プライバシーや機密保持が心配」「記録時の簡便操作が必須」という、プロダクトが乗り越えるべき現実的な壁も突きつけられた。\n\n彼はさらに、元同僚という最も身近な顧客候補にアタックする。食事の席でのリラックスした対話の中から、核心を突くフィードバックが返ってきた。\n\n> 「使い始めてから便利になるのに時間がかかりそうだなー」\n> 「プライバシーが心配。特に会社関連の情報は機密規定に違反しそう。」\n> 「この機能だけでは一つのアプリとしては物足りない。」\n\nそして、決定的な一言。「お金ははらえないなー」。\n\nSNSでの仮ローンチでも、反応は得られなかった。共感されるはずの「課題」と、彼らが考えた「解決策」との間には、まだ埋めがたい溝があった。ユーザーは、その価値を自分ごととして感じてはくれなかった。この静かな、しかし、重い現実は、彼に根本的な問い直しを迫るのに十分だった。\n\n## 第四章: 本質への問い直し\n\n「今は買ってない」\n\n最終盤、想定顧客が見つかったかを問われた彼の答えは、潔いほど率直だった。その理由に、彼の誠実さが凝縮されている。\n\n> **「MVPを作っている自分自身、『これでは課題解決にならない・・・・』と感じ始めているため、買ってくれる人はいないと考える。」**\n\n他者からのフィードバックだけではない。プロダクトを最も深く知る開発者である彼自身が、その価値に疑問を抱き始めていたのだ。これは失敗ではない。むしろ、作り手としての責任感と、ユーザーへの真摯な態度の表れだった。彼は、自分が納得できないものを世に問うことはできなかった。\n\n「ピボットします」。その短い宣言には、大きな決意が込められていた。これまでのアプローチを一度手放し、もう一度、課題の本質に立ち返る。彼が見つけた光は、「MVPは、早めの公開が必須。見せられるものがあると話しやすい」という学びだった。不完全でもいい。早く形にし、対話し、軌道修正する。そのサイクルの重要性を、彼は身をもって学んだのだ。\n\nWALL PITCH（ポスター発表）で彼が掲げたメッセージは、原点に回帰していた。「情報が氾濫する現状をなんとかしたい」。プロダクトの機能説明ではなく、彼が最初に感じた「問い」そのものを、再び力強く投げかけた。それは、一度立ち止まり、再び歩き出すための覚悟の表明だった。\n\n## エピローグ: 振り返りと学び\n\n14週間の旅路の終わり。彼は、静かにこれまでの軌跡を言葉に紡いだ。\n\nそこには、プロダクトの成功物語はない。代わりにあったのは、仮説が砕かれ、現実の壁にぶつかり、「これでは課題解決にならない」と自ら判断を下した、誠実な探求の記録だった。\n\n> 「最初のMVPは自身も納得できず、『これでは課題解決にならない』と判断。根本的なUI/UXや利用シーンの再設計と、課題の再定義に向けてピボットを決意。」\n\n彼は、情報の迷子をゼロにしたいと願った。その想いは変わらない。しかし、その届け方は一つではなかった。顧客からの「便利そうだが今は必要ない」という声を受け止め、彼は「課題の再定義とユーザー調査を継続予定」と未来を見据える。\n\nこの物語は、一つのプロダクトが完成しなかったという点で、見方によっては「うまくいかなかった」話かもしれない。しかし、その本質はそこにはない。\n\n日常の小さな違和感から問いを立て、他者に共感し、仲間と形にし、現実にぶつかり、そして、作り手として自ら「NO」を突きつける。その上で、再び課題の原点に立ち返る。この一連のプロセスこそが、彼がこの旅で得た最大の「学び」であり、揺るぎない「資産」なのだ。\n\n「あの情報、どこだっけ？」という最初の問いは、まだ答えを見つけていない。しかし彼は、その問いと共に歩み続けるための、コンパスを手に入れた。それは、ユーザーの声に耳を傾け、自分自身の内なる声に誠実であること。この物語は、終わりではなく、新たな探求の始まりを告げている。\n\n---\n\n### 付録: 開発ジャーニー概要\n\n- **期間**: 14週間\n- **提出課題数**: 17課題（json準拠）\n- **主要なピボット**: 顧客からのフィードバックと自己評価に基づき、「解決策が課題解決になっていない」と判断し、ピボットを決意。\n- **最終プロダクト**: 情報横断検索支援ツール（開発中・ピボット検討段階）\n- **核心的な学び**: MVP（最小限の価値提供プロダクト）を早期に作り、現実世界に問うことの重要性。そして、作り手自身が価値を確信できない場合は、勇気を持って立ち止まり、問い直すことの誠実さ。\n\n---\n\n*この物語は、`b3e7070a5d57.json` のデータをもとに、構成作家エージェントが執筆しました。（生成日時: 2024-05-23 15:00:00）*"
}